CHANGES.txt
MANIFEST.in
README.md
ingranalyze.py
setup.py
ingranalyze.egg-info/PKG-INFO
ingranalyze.egg-info/SOURCES.txt
ingranalyze.egg-info/dependency_links.txt
ingranalyze.egg-info/requires.txt
ingranalyze.egg-info/top_level.txt
src/__init__.py
src/bioquali.py
src/graph_parser.py
src/query.py
src/sif_parser.py
src/utils.py
src/encodings/compute_repair_options.gringo
src/encodings/dynamic_diagnosis.gringo
src/encodings/pm_consistency.gringo
src/encodings/pm_guess_inputs.gringo
src/encodings/pm_mic.gringo
src/encodings/pm_prediction.gringo
src/encodings/prediction_core.gringo
src/encodings/reduction.lp
src/encodings/repair_cardinality.gringo
src/encodings/repair_core.gringo
src/encodings/repair_subset.gringo
src/encodings/subset_minimal_repair_obs.gringo