Metadata-Version: 2.1
Name: ingranalyze
Version: 1.5.6
Summary: Influence graph analysis, consistency check, diagnosis, repair and prediction.
Home-page: http://bioasp.github.io/ingranalyze/
Author: Sven Thiele
Author-email: sthiele78@gmail.com
License: GPLv3+
Platform: UNKNOWN
